LICENSE
MANIFEST.in
README.md
pyproject.toml
setup.cfg
setup.py
src/__init__.py
src/PyAltiumRun.egg-info/PKG-INFO
src/PyAltiumRun.egg-info/SOURCES.txt
src/PyAltiumRun.egg-info/dependency_links.txt
src/PyAltiumRun.egg-info/not-zip-safe
src/PyAltiumRun.egg-info/requires.txt
src/PyAltiumRun.egg-info/top_level.txt
src/PyAltiumRunTop/AltiumRun.py
src/PyAltiumRunTop/AltiumRun15.py
src/PyAltiumRunTop/AltiumRunAd.py
src/PyAltiumRunTop/AltiumRunAd15.py
src/PyAltiumRunTop/AltiumRunEnv.py
src/PyAltiumRunTop/AltiumRunEnv15.py
src/PyAltiumRunTop/AltiumRunEnvNew.py
src/PyAltiumRunTop/AltiumRunexe.py
src/PyAltiumRunTop/AltiumRunexe15.py
src/PyAltiumRunTop/__init__.py
src/PyAltiumRunTop/py.typed
src/PyAltiumRunTop.egg-info/PKG-INFO
src/PyAltiumRunTop.egg-info/SOURCES.txt
src/PyAltiumRunTop.egg-info/dependency_links.txt
src/PyAltiumRunTop.egg-info/not-zip-safe
src/PyAltiumRunTop.egg-info/requires.txt
src/PyAltiumRunTop.egg-info/top_level.txt
src/PyAltiumRunTop/helpers/AltiumHelper.py
src/PyAltiumRunTop/helpers/__init__.py
src/PyAltiumRunTop/helpers15/AltiumHelper.py
src/PyAltiumRunTop/helpers15/__init__.py
src/PyAltiumRunTop/scriptingbase/__init__.py
src/PyAltiumRunTop/scriptingbase/logger.pas
src/PyAltiumRunTop/scriptingbase/main.pas
src/PyAltiumRunTop/scriptingbase/updateSitNum0302.pas