Metadata-Version: 2.1
Name: PyAltiumRunTop
Version: 0.2.4.9
Summary: A library that can run scripts in altium designer
Home-page: https://github.com/wqh0109663/PyAltiumRun
Author: Dylan Gybels,wqh0109663
Author-email: dylangybels@gmail.com,wqh0109663@gmail.com
License: MIT
Keywords: Altium,Scripting,Runner
Platform: win32
Classifier: Development Status :: 3 - Alpha
Classifier: Programming Language :: Python :: 3
Classifier: Programming Language :: Python :: 3 :: Only
Classifier: Programming Language :: Python :: 3.6
Classifier: Programming Language :: Python :: 3.7
Classifier: Programming Language :: Python :: 3.8
Classifier: Programming Language :: Python :: 3.9
Requires-Python: >=3.6
Provides-Extra: testing
License-File: LICENSE
